README.md
setup.py
auto_retry_sshfs/__init__.py
auto_retry_sshfs/auto_retry_sshfs.py
auto_retry_sshfs/cli.py
auto_retry_sshfs.egg-info/PKG-INFO
auto_retry_sshfs.egg-info/SOURCES.txt
auto_retry_sshfs.egg-info/dependency_links.txt
auto_retry_sshfs.egg-info/entry_points.txt
auto_retry_sshfs.egg-info/top_level.txt