Metadata-Version: 2.1
Name: auto-retry-sshfs
Version: 1.0.0
Summary: Ridiculous tool that automatically retries sshfs for you over an unreliable connection.
Home-page: https://github.com/kavigupta/auto-retry-sshfs
Author: Kavi Gupta
Author-email: autoretrysshfs@kavigupta.org
License: UNKNOWN
Platform: UNKNOWN
Classifier: Programming Language :: Python :: 3.6
Classifier: Programming Language :: Python :: 3.7
Classifier: Programming Language :: Python :: 3.8
Classifier: Operating System :: OS Independent
Requires-Python: >=3.6
